{
    "metaDataVersion": "1.0.0",
    "category": "com.microchip.ide.project",
    "content": {
        "metaDataVersion": "1.1.0",
        "name": "com.microchip.mcu8.studio.project.atmega4809-getting-started-with-tca-studio",
        "version": "1.0.0",
        "displayName": "Getting Started with Timer/Counter Type A (TCA) Examples (Microchip Studio)",
        "projectName": "atmega4809-getting-started-with-tca-studio",
        "shortDescription": "This repository contains examples of bare metal source code for Timer/Counter Type A (TCA), as described in the TB3217-Getting Started with Timer/Counter Type A (TCA) document.",
        "ide": {
            "name": "STUDIO",
            "semverRange": ">=7.0.2397"
        },
        "compiler": [
			{
				"name": "avr-gcc",
				"semverRange": "^5.4.0"
			}
		],
        "dfp": {
            "name": "ATmega_DFP",
            "semverRange": "^1.6.364"
        },
        "configurator": {
            "name": "N/A",
            "semverRange": ""
        },
        "device": {
            "metaDataVersion": "1.0.0",
            "category": "com.microchip.portal.contentRef",
            "content": {
                "metaDataVersion": "1.0.0",
                "category": "com.microchip.device",
                "name": "ATmega4809",
                "versionRange": "*"
            }
        },
        "author": "Microchip",
        "subcategories": [
            [
                "Peripherals",
                "TCA"
            ],
            [
                "Development Kit",
                "ATmega4809 Xplained Pro"
            ]
        ],
        "peripherals": [
            "TCA"
        ],
        "keywords": [
            "Bare Metal"
        ],
		"additionalData": {
			"longDescription": {
				"metaDataVersion": "1.0.0",
				"category": "com.microchip.portal.fileRef",
				"content": {
					"metaDataVersion": "1.0.0",
					"fileName": "./README.md",
					"mimeType": "text/markdown"
				}
			}
		}
	}
}
